build/lib/kerastorch/__init__.py
build/lib/kerastorch/data.py
build/lib/kerastorch/eda.py
build/lib/kerastorch/email.py
build/lib/kerastorch/hugmodel.py
build/lib/kerastorch/kerascallbacks.py
build/lib/kerastorch/kerasmodel.py
build/lib/kerastorch/metrics.py
build/lib/kerastorch/pbar.py
build/lib/kerastorch/plots.py
build/lib/kerastorch/soup.py
build/lib/kerastorch/summary.py
build/lib/kerastorch/utils.py
build/lib/kerastorch/chat/__init__.py
build/lib/kerastorch/chat/chatglm.py
build/lib/kerastorch/chat/chatgpt.py
build/lib/kerastorch/models/__init__.py
build/lib/kerastorch/models/resnet.py
build/lib/kerastorch/models/ssd.py
build/lib/kerastorch/models/unet.py
build/lib/kerastorch/tools/catboost.py
kerastorch/__init__.py
kerastorch/data.py
kerastorch/eda.py
kerastorch/email.py
kerastorch/hugmodel.py
kerastorch/kerascallbacks.py
kerastorch/kerasmodel.py
kerastorch/metrics.py
kerastorch/pbar.py
kerastorch/plots.py
kerastorch/soup.py
kerastorch/summary.py
kerastorch/utils.py
kerastorch/chat/__init__.py
kerastorch/chat/chatglm.py
kerastorch/chat/chatgpt.py
kerastorch/models/__init__.py
kerastorch/models/resnet.py
kerastorch/models/ssd.py
kerastorch/models/unet.py
kerastorch/tools/catboost.py
kerastorch-1.0.3.dist-info/LICENSE.txt
kerastorch-1.0.3.dist-info/METADATA
kerastorch-1.0.3.dist-info/WHEEL
kerastorch-1.0.3.dist-info/top_level.txt
kerastorch-1.0.3.dist-info/RECORD
